axa_fr_ml_cli/__init__.py
axa_fr_ml_cli/environment.py
axa_fr_ml_cli/run.py
axa_fr_ml_cli/modules/__init__.py
axa_fr_ml_cli/modules/extraction/__init__.py
axa_fr_ml_cli/modules/extraction/extraction.py
axa_fr_ml_cli/modules/extraction/extraction_step.py
axa_fr_ml_cli/modules/extraction/ml_cli.py
axa_fr_ml_cli/modules/ingestion_chunk/__init__.py
axa_fr_ml_cli/modules/ingestion_chunk/chunk_files.py
axa_fr_ml_cli/modules/ingestion_chunk/data_ingestion.py
axa_fr_ml_cli/modules/ingestion_chunk/data_ingestion_step.py
axa_fr_ml_cli/modules/ingestion_chunk/tests/__init__.py
axa_fr_ml_cli/modules/ingestion_chunk/tests/test_chunk_files.py
axa_fr_ml_cli/modules/save/__init__.py
axa_fr_ml_cli/modules/save/aggregate_output.py
axa_fr_ml_cli/modules/save/save.py
axa_fr_ml_cli/modules/save/save_step.py
axa_fr_ml_cli/modules/save/tests/__init__.py
axa_fr_ml_cli/modules/save/tests/test_aggregate_output.py
axa_fr_ml_cli/pipelines/__init__.py
axa_fr_ml_cli/pipelines/train_pipeline.py
ml_cli/__init__.py
ml_cli/environment.py
ml_cli/run.py
ml_cli/modules/__init__.py
ml_cli/modules/extraction/__init__.py
ml_cli/modules/extraction/extraction.py
ml_cli/modules/extraction/extraction_step.py
ml_cli/modules/extraction/ml_cli.py
ml_cli/modules/ingestion_chunk/__init__.py
ml_cli/modules/ingestion_chunk/chunk_files.py
ml_cli/modules/ingestion_chunk/data_ingestion.py
ml_cli/modules/ingestion_chunk/data_ingestion_step.py
ml_cli/modules/ingestion_chunk/tests/__init__.py
ml_cli/modules/ingestion_chunk/tests/test_chunk_files.py
ml_cli/modules/save/__init__.py
ml_cli/modules/save/aggregate_output.py
ml_cli/modules/save/save.py
ml_cli/modules/save/save_step.py
ml_cli/modules/save/tests/__init__.py
ml_cli/modules/save/tests/test_aggregate_output.py
ml_cli/pipelines/__init__.py
ml_cli/pipelines/train_pipeline.py
axa_fr_ml_cli-0.0.1.dist-info/LICENSE
axa_fr_ml_cli-0.0.1.dist-info/METADATA
axa_fr_ml_cli-0.0.1.dist-info/WHEEL
axa_fr_ml_cli-0.0.1.dist-info/top_level.txt
axa_fr_ml_cli-0.0.1.dist-info/RECORD
